[{"raw":"<l n=\"1\"><milestone unit=\"Para\" ed=\"P\"/>ἑστίη, ἥτε ἄνακτος Ἀπόλλωνος ἑκάτοιο </l>","text":"ἑστίη, ἥτε ἄνακτος Ἀπόλλωνος ἑκάτοιο","n":"1","elements":[{"attributes":{"ed":"P","unit":"Para"},"name":"milestone","start_offset":0,"end_offset":0}]},{"raw":"<l n=\"2\">Πυθοῖ ἐν ἠγαθέῃ ἱερὸν δόμον ἀμφιπολεύεις, </l>","text":"Πυθοῖ ἐν ἠγαθέῃ ἱερὸν δόμον ἀμφιπολεύεις,","n":"2","elements":[]},{"raw":"<l n=\"3\">αἰεὶ σῶν πλοκάμων ἀπολείβεται ὑγρὸν ἔλαιον· </l>","text":"αἰεὶ σῶν πλοκάμων ἀπολείβεται ὑγρὸν ἔλαιον·","n":"3","elements":[]},{"raw":"<l n=\"4\">ἔρχεο τόνδʼ ἀνὰ οἶκον, ἕνʼ ἔρχεο θυμὸν ἔχουσα </l>","text":"ἔρχεο τόνδʼ ἀνὰ οἶκον, ἕνʼ ἔρχεο θυμὸν ἔχουσα","n":"4","elements":[]},{"raw":"<l n=\"5\">σὺν Διὶ μητιόεντι· χάριν δʼ ἅμʼ ὄπασσον ἀοιδῇ. </l>","text":"σὺν Διὶ μητιόεντι· χάριν δʼ ἅμʼ ὄπασσον ἀοιδῇ.","n":"5","elements":[]}]